ml1-10/__init__.py
ml1-10/p1.py
ml1-10/p10.py
ml1-10/p2.py
ml1-10/p3.py
ml1-10/p4.py
ml1-10/p5.py
ml1-10/p6.py
ml1-10/p7.py
ml1-10/p8.py
ml1-10/p9.py
ml1_10/__init__.py
ml1_10/p1.py
ml1_10/p10.py
ml1_10/p2.py
ml1_10/p3.py
ml1_10/p4.py
ml1_10/p5.py
ml1_10/p6.py
ml1_10/p7.py
ml1_10/p8.py
ml1_10/p9.py
ml1_10-0.1.0.dist-info/METADATA
ml1_10-0.1.0.dist-info/WHEEL
ml1_10-0.1.0.dist-info/top_level.txt
ml1_10-0.1.0.dist-info/RECORD
