Metadata-Version: 2.1
Name: ml1-10
Version: 0.1.0
Summary: ML tool for data visualization and outlier detection
Home-page: https://github.com/Veeresh-hp/ml1_10
Author: veeresh
Author-email: veeresh04@gmail.com
Classifier: Programming Language :: Python :: 3
Classifier: Operating System :: OS Independent
Requires-Python: >=3.7
Requires-Dist: pandas
Requires-Dist: numpy
Requires-Dist: matplotlib
Requires-Dist: seaborn
Requires-Dist: scikit-learn
